[{"latitude":"39.09","longitude":"-94.58","state":"MO"},{"latitude":"37.45","longitude":"-122.1","state":"CA"},{"latitude":"42.13","longitude":"-121.81","state":"OR"},{"latitude":"42.84","longitude":"-91.8","state":"IA"},{"latitude":"41.99","longitude":"-92.58","state":"IA"},{"latitude":"40.77","longitude":"-73.95","state":"NY"},{"latitude":"38.57","longitude":"-91.96","state":"MO"},{"latitude":"36.94","longitude":"-77.4","state":"VA"},{"latitude":"44.05","longitude":"-123.11","state":"OR"},{"latitude":"39.73","longitude":"-75.4","state":"NJ"},{"latitude":"36.73","longitude":"-76.04","state":"VA"},{"latitude":"37.27","longitude":"-79.95","state":"VA"},{"latitude":"47.14","longitude":"-122.44","state":"WA"},{"latitude":"39.86","longitude":"-75.13","state":"NJ"},{"latitude":"40.99","longitude":"-72.29","state":"NY"},{"latitude":"41.9","longitude":"-75.33","state":"PA"},{"latitude":"34.98","longitude":"-119.8","state":"CA"},{"latitude":"40.77","longitude":"-97.05","state":"NE"},{"latitude":"40.53","longitude":"-75.49","state":"PA"},{"latitude":"43.16","longitude":"-77.61","state":"NY"},{"latitude":"37.99","longitude":"-122.0","state":"CA"},{"latitude":"37.87","longitude":"-89.94","state":"MO"},{"latitude":"47.25","longitude":"-122.44","state":"WA"},{"latitude":"42.21","longitude":"-72.64","state":"MA"},{"latitude":"40.3","longitude":"-75.53","state":"PA"},{"latitude":"36.69","longitude":"-77.53","state":"VA"},{"latitude":"48.95","longitude":"-122.43","state":"WA"},{"latitude":"36.31","longitude":"-95.61","state":"OK"},{"latitude":"42.25","longitude":"-71.12","state":"MA"},{"latitude":"46.36","longitude":"-123.75","state":"WA"},{"latitude":"36.24","longitude":"-96.26","state":"OK"},{"latitude":"40.28","longitude":"-79.79","state":"PA"},{"latitude":"40.5","longitude":"-95.03","state":"MO"},{"latitude":"38.93","longitude":"-77.18","state":"VA"},{"latitude":"39.74","longitude":"-94.0","state":"MO"},{"latitude":"47.37","longitude":"-122.71","state":"WA"},{"latitude":"36.95","longitude":"-90.15","state":"MO"},{"latitude":"35.46","longitude":"-97.51","state":"OK"},{"latitude":"34.05","longitude":"-117.24","state":"CA"},{"latitude":"47.41","longitude":"-122.63","state":"WA"},{"latitude":"34.27","longitude":"-118.71","state":"CA"},{"latitude":"37.39","longitude":"-94.09","state":"MO"},{"latitude":"39.54","longitude":"-122.57","state":"CA"},{"latitude":"39.27","longitude":"-114.99","state":"NV"},{"latitude":"42.41","longitude":"-70.99","state":"MA"},{"latitude":"37.25","longitude":"-121.92","state":"CA"},{"latitude":"40.43","longitude":"-79.97","state":"PA"},{"latitude":"40.79","longitude":"-74.47","state":"NJ"},{"latitude":"42.68","longitude":"-76.95","state":"NY"},{"latitude":"40.45","longitude":"-94.84","state":"MO"},{"latitude":"41.88","longitude":"-98.55","state":"NE"},{"latitude":"37.49","longitude":"-92.29","state":"MO"},{"latitude":"40.93","longitude":"-74.54","state":"NJ"},{"latitude":"36.71","longitude":"-80.81","state":"VA"},{"latitude":"41.57","longitude":"-93.61","state":"IA"},{"latitude":"42.13","longitude":"-71.96","state":"MA"},{"latitude":"44.05","longitude":"-120.09","state":"OR"},{"latitude":"42.3","longitude":"-78.02","state":"NY"},{"latitude":"36.12","longitude":"-115.28","state":"NV"},{"latitude":"39.87","longitude":"-92.02","state":"MO"},{"latitude":"40.17","longitude":"-78.37","state":"PA"},{"latitude":"47.63","longitude":"-122.34","state":"WA"},{"latitude":"38.86","longitude":"-77.77","state":"VA"},{"latitude":"38.01","longitude":"-90.21","state":"MO"},{"latitude":"40.04","longitude":"-76.3","state":"PA"},{"latitude":"42.59","longitude":"-73.7","state":"NY"},{"latitude":"39.8","longitude":"-74.93","state":"NJ"},{"latitude":"39.95","longitude":"-75.16","state":"PA"},{"latitude":"42.637549","longitude":"-75.672508","state":"NY"},{"latitude":"36.03","longitude":"-95.78","state":"OK"},{"latitude":"37.05","longitude":"-122.05","state":"CA"},{"latitude":"42.42","longitude":"-94.86","state":"IA"},{"latitude":"36.12","longitude":"-95.91","state":"OK"},{"latitude":"42.61","longitude":"-120.57","state":"OR"},{"latitude":"33.752886","longitude":"-116.055617","state":"CA"},{"latitude":"43.07","longitude":"-76.0","state":"NY"},{"latitude":"42.55","longitude":"-71.26","state":"MA"},{"latitude":"40.45","longitude":"-74.43","state":"NJ"},{"latitude":"42.57","longitude":"-73.88","state":"NY"},{"latitude":"34.17","longitude":"-118.54","state":"CA"},{"latitude":"41.73","longitude":"-74.67","state":"NY"},{"latitude":"40.43","longitude":"-79.97","state":"PA"},{"latitude":"42.45","longitude":"-79.0","state":"NY"},{"latitude":"42.05","longitude":"-79.66","state":"NY"},{"latitude":"32.73","longitude":"-117.03","state":"CA"},{"latitude":"40.72","longitude":"-73.7","state":"NY"},{"latitude":"35.45","longitude":"-97.51","state":"OK"},{"latitude":"41.78","longitude":"-73.69","state":"NY"},{"latitude":"41.13","longitude":"-73.79","state":"NY"},{"latitude":"45.92","longitude":"-123.97","state":"OR"},{"latitude":"42.48","longitude":"-71.15","state":"MA"},{"latitude":"47.0","longitude":"-117.35","state":"WA"},{"latitude":"45.89","longitude":"-122.81","state":"OR"},{"latitude":"39.983153","longitude":"-75.748055","state":"PA"},{"latitude":"45.84","longitude":"-120.76","state":"WA"},{"latitude":"41.0","longitude":"-78.11","state":"PA"},{"latitude":"40.86","longitude":"-92.33","state":"IA"},{"latitude":"35.46","longitude":"-97.51","state":"OK"},{"latitude":"40.16","longitude":"-78.23","state":"PA"},{"latitude":"42.96","longitude":"-94.44","state":"IA"},{"latitude":"43.0","longitude":"-96.05","state":"IA"},{"latitude":"42.26","longitude":"-96.86","state":"NE"},{"latitude":"33.99","longitude":"-117.44","state":"CA"},{"latitude":"41.19","longitude":"-95.42","state":"IA"},{"latitude":"38.13","longitude":"-90.56","state":"MO"},{"latitude":"41.11","longitude":"-75.56","state":"PA"},{"latitude":"44.29","longitude":"-98.42","state":"SD"},{"latitude":"44.36","longitude":"-100.37","state":"SD"},{"latitude":"36.38","longitude":"-120.13","state":"CA"},{"latitude":"40.79","longitude":"-79.18","state":"PA"},{"latitude":"35.4","longitude":"-94.6","state":"OK"},{"latitude":"36.06","longitude":"-95.94","state":"OK"},{"latitude":"34.19","longitude":"-118.82","state":"CA"},{"latitude":"34.5","longitude":"-98.98","state":"OK"},{"latitude":"41.84","longitude":"-75.0","state":"NY"},{"latitude":"38.01","longitude":"-77.51","state":"VA"},{"latitude":"40.81","longitude":"-96.68","state":"NE"},{"latitude":"43.48","longitude":"-73.89","state":"NY"},{"latitude":"40.75","longitude":"-74.41","state":"NJ"},{"latitude":"38.79","longitude":"-117.11","state":"NV"},{"latitude":"38.63","longitude":"-90.24","state":"MO"},{"latitude":"42.46","longitude":"-97.9","state":"NE"},{"latitude":"41.57","longitude":"-93.61","state":"IA"},{"latitude":"36.77","longitude":"-89.38","state":"MO"},{"latitude":"35.08","longitude":"-96.39","state":"OK"},{"latitude":"40.43","longitude":"-79.97","state":"PA"},{"latitude":"42.75","longitude":"-71.03","state":"MA"},{"latitude":"40.56","longitude":"-78.91","state":"PA"},{"latitude":"37.3","longitude":"-120.87","state":"CA"},{"latitude":"43.59","longitude":"-97.29","state":"SD"},{"latitude":"33.94","longitude":"-116.97","state":"CA"},{"latitude":"41.21","longitude":"-73.57","state":"NY"},{"latitude":"40.01","longitude":"-101.93","state":"NE"},{"latitude":"39.49","longitude":"-123.36","state":"CA"},{"latitude":"41.02","longitude":"-100.36","state":"NE"},{"latitude":"40.49","longitude":"-92.69","state":"MO"},{"latitude":"44.0","longitude":"-76.04","state":"NY"},{"latitude":"41.71","longitude":"-80.13","state":"PA"},{"latitude":"40.32","longitude":"-78.91","state":"PA"},{"latitude":"40.59","longitude":"-73.81","state":"NY"},{"latitude":"41.25","longitude":"-94.76","state":"IA"},{"latitude":"37.3","longitude":"-122.09","state":"CA"},{"latitude":"43.26","longitude":"-99.71","state":"SD"},{"latitude":"41.05","longitude":"-76.24","state":"PA"},{"latitude":"42.54","longitude":"-78.89","state":"NY"},{"latitude":"47.94","longitude":"-122.24","state":"WA"},{"latitude":"47.66","longitude":"-117.43","state":"WA"},{"latitude":"39.04","longitude":"-74.86","state":"NJ"},{"latitude":"40.44","longitude":"-99.37","state":"NE"},{"latitude":"35.37","longitude":"-118.99","state":"CA"},{"latitude":"40.58","longitude":"-74.14","state":"NY"},{"latitude":"40.71","longitude":"-73.99","state":"NY"},{"latitude":"39.25","longitude":"-119.95","state":"NV"},{"latitude":"36.83","longitude":"-76.29","state":"VA"},{"latitude":"41.74","longitude":"-73.58","state":"NY"},{"latitude":"42.66","longitude":"-77.05","state":"NY"},{"latitude":"43.32","longitude":"-95.15","state":"IA"},{"latitude":"39.34","longitude":"-121.23","state":"CA"},{"latitude":"40.84","longitude":"-74.05","state":"NJ"},{"latitude":"37.88","longitude":"-122.29","state":"CA"},{"latitude":"42.72","longitude":"-95.18","state":"IA"},{"latitude":"41.89","longitude":"-91.15","state":"IA"},{"latitude":"34.0","longitude":"-118.25","state":"CA"},{"latitude":"34.06","longitude":"-118.35","state":"CA"},{"latitude":"47.92","longitude":"-122.09","state":"WA"},{"latitude":"42.31","longitude":"-71.93","state":"MA"},{"latitude":"38.31","longitude":"-122.7","state":"CA"},{"latitude":"36.53","longitude":"-120.11","state":"CA"},{"latitude":"42.41","longitude":"-71.68","state":"MA"},{"latitude":"40.11","longitude":"-78.96","state":"PA"},{"latitude":"40.651378","longitude":"-73.870779","state":"NY"},{"latitude":"36.03","longitude":"-95.78","state":"OK"},{"latitude":"44.5","longitude":"-117.65","state":"OR"},{"latitude":"37.72","longitude":"-121.03","state":"CA"},{"latitude":"42.37","longitude":"-94.43","state":"IA"},{"latitude":"37.03","longitude":"-77.09","state":"VA"},{"latitude":"47.5","longitude":"-122.0","state":"WA"},{"latitude":"42.59","longitude":"-78.93","state":"NY"},{"latitude":"37.85","longitude":"-121.62","state":"CA"},{"latitude":"37.12","longitude":"-81.51","state":"VA"},{"latitude":"36.63","longitude":"-114.62","state":"NV"},{"latitude":"38.17","longitude":"-121.52","state":"CA"},{"latitude":"37.99","longitude":"-77.22","state":"VA"},{"latitude":"41.4","longitude":"-75.66","state":"PA"},{"latitude":"40.71","longitude":"-73.99","state":"NY"},{"latitude":"40.27","longitude":"-76.88","state":"PA"},{"latitude":"40.75","longitude":"-74.98","state":"NJ"},{"latitude":"42.06","longitude":"-70.8","state":"MA"},{"latitude":"40.64","longitude":"-73.94","state":"NY"},{"latitude":"36.13","longitude":"-97.07","state":"OK"},{"latitude":"41.54","longitude":"-98.53","state":"NE"},{"latitude":"36.665794","longitude":"-96.398424","state":"OK"},{"latitude":"38.16","longitude":"-78.83","state":"VA"},{"latitude":"40.45","longitude":"-80.25","state":"PA"},{"latitude":"40.64","longitude":"-73.94","state":"NY"},{"latitude":"41.24","longitude":"-75.87","state":"PA"},{"latitude":"41.89","longitude":"-93.53","state":"IA"},{"latitude":"34.87","longitude":"-99.5","state":"OK"},{"latitude":"38.55","longitude":"-121.49","state":"CA"},{"latitude":"42.338947","longitude":"-70.919635","state":"MA"},{"latitude":"45.17","longitude":"-123.83","state":"OR"},{"latitude":"39.12","longitude":"-123.28","state":"CA"},{"latitude":"34.15","longitude":"-118.09","state":"CA"},{"latitude":"42.83","longitude":"-93.22","state":"IA"},{"latitude":"37.67","longitude":"-77.29","state":"VA"},{"latitude":"43.04","longitude":"-76.14","state":"NY"},{"latitude":"33.7","longitude":"-116.4","state":"CA"},{"latitude":"46.62","longitude":"-123.64","state":"WA"},{"latitude":"33.75","longitude":"-118.3","state":"CA"},{"latitude":"40.81","longitude":"-96.68","state":"NE"},{"latitude":"37.84","longitude":"-94.35","state":"MO"},{"latitude":"36.06","longitude":"-115.31","state":"NV"},{"latitude":"41.67","longitude":"-70.11","state":"MA"},{"latitude":"42.87","longitude":"-98.7","state":"NE"},{"latitude":"43.36","longitude":"-91.22","state":"IA"},{"latitude":"42.81","longitude":"-96.05","state":"IA"},{"latitude":"45.33","longitude":"-100.12","state":"SD"},{"latitude":"43.04","longitude":"-76.14","state":"NY"},{"latitude":"36.12","longitude":"-95.91","state":"OK"},{"latitude":"40.86","longitude":"-121.91","state":"CA"},{"latitude":"38.88","longitude":"-122.55","state":"CA"},{"latitude":"38.83","longitude":"-77.99","state":"VA"},{"latitude":"37.33","longitude":"-121.89","state":"CA"},{"latitude":"42.58","longitude":"-99.53","state":"NE"},{"latitude":"33.6","longitude":"-117.71","state":"CA"},{"latitude":"39.32","longitude":"-78.29","state":"VA"},{"latitude":"40.6","longitude":"-78.73","state":"PA"},{"latitude":"34.14","longitude":"-118.14","state":"CA"},{"latitude":"40.09","longitude":"-76.67","state":"PA"},{"latitude":"37.6","longitude":"-75.68","state":"VA"},{"latitude":"36.7","longitude":"-81.43","state":"VA"},{"latitude":"40.84","longitude":"-73.87","state":"NY"},{"latitude":"38.71","longitude":"-123.33","state":"CA"},{"latitude":"42.88","longitude":"-78.85","state":"NY"},{"latitude":"46.41","longitude":"-122.99","state":"WA"},{"latitude":"42.2","longitude":"-95.95","state":"IA"},{"latitude":"47.25","longitude":"-122.44","state":"WA"},{"latitude":"43.39","longitude":"-76.48","state":"NY"},{"latitude":"34.23","longitude":"-98.68","state":"OK"},{"latitude":"36.37","longitude":"-95.85","state":"OK"},{"latitude":"40.1","longitude":"-94.0","state":"MO"},{"latitude":"41.241656","longitude":"-76.747251","state":"PA"},{"latitude":"39.82","longitude":"-75.82","state":"PA"},{"latitude":"40.322965","longitude":"-79.653388","state":"PA"},{"latitude":"41.96","longitude":"-74.28","state":"NY"},{"latitude":"40.38","longitude":"-95.84","state":"NE"},{"latitude":"40.83","longitude":"-79.79","state":"PA"},{"latitude":"38.8","longitude":"-119.32","state":"NV"},{"latitude":"37.08","longitude":"-121.61","state":"CA"},{"latitude":"36.07","longitude":"-115.21","state":"NV"},{"latitude":"36.6","longitude":"-94.45","state":"MO"},{"latitude":"40.11","longitude":"-78.81","state":"PA"},{"latitude":"35.11","longitude":"-95.23","state":"OK"},{"latitude":"40.74","longitude":"-74.15","state":"NJ"},{"latitude":"47.39","longitude":"-122.23","state":"WA"},{"latitude":"47.37","longitude":"-122.84","state":"WA"},{"latitude":"40.8","longitude":"-75.61","state":"PA"},{"latitude":"39.88","longitude":"-75.3","state":"PA"},{"latitude":"34.02","longitude":"-95.86","state":"OK"},{"latitude":"34.23","longitude":"-119.07","state":"CA"},{"latitude":"38.02","longitude":"-122.75","state":"CA"},{"latitude":"42.45","longitude":"-73.58","state":"NY"},{"latitude":"38.22","longitude":"-79.16","state":"VA"},{"latitude":"41.64","longitude":"-75.59","state":"PA"},{"latitude":"41.82","longitude":"-90.75","state":"IA"},{"latitude":"42.99","longitude":"-77.49","state":"NY"},{"latitude":"41.24","longitude":"-95.85","state":"IA"},{"latitude":"36.4","longitude":"-90.02","state":"MO"},{"latitude":"46.97","longitude":"-124.14","state":"WA"},{"latitude":"36.79","longitude":"-89.96","state":"MO"},{"latitude":"41.27","longitude":"-70.1","state":"MA"},{"latitude":"41.05","longitude":"-94.36","state":"IA"},{"latitude":"42.64","longitude":"-91.81","state":"IA"},{"latitude":"41.2","longitude":"-73.98","state":"NY"},{"latitude":"34.25","longitude":"-119.2","state":"CA"},{"latitude":"40.44","longitude":"-79.98","state":"PA"},{"latitude":"40.36","longitude":"-75.3","state":"PA"},{"latitude":"34.16","longitude":"-118.26","state":"CA"},{"latitude":"38.82","longitude":"-77.08","state":"VA"},{"latitude":"35.85","longitude":"-95.31","state":"OK"},{"latitude":"42.68","longitude":"-72.18","state":"MA"},{"latitude":"40.18","longitude":"-75.0","state":"PA"},{"latitude":"34.51","longitude":"-118.68","state":"CA"},{"latitude":"37.41","longitude":"-122.13","state":"CA"},{"latitude":"40.53","longitude":"-75.19","state":"PA"},{"latitude":"40.44","longitude":"-74.54","state":"NJ"},{"latitude":"40.004885","longitude":"-77.77637","state":"PA"},{"latitude":"40.43","longitude":"-79.97","state":"PA"},{"latitude":"42.29","longitude":"-74.15","state":"NY"},{"latitude":"42.26","longitude":"-92.69","state":"IA"},{"latitude":"40.72","longitude":"-73.74","state":"NY"},{"latitude":"34.52","longitude":"-116.88","state":"CA"},{"latitude":"44.35","longitude":"-103.76","state":"SD"},{"latitude":"40.77","longitude":"-97.81","state":"NE"},{"latitude":"42.6","longitude":"-76.18","state":"NY"},{"latitude":"40.6","longitude":"-97.85","state":"NE"},{"latitude":"36.67","longitude":"-93.86","state":"MO"},{"latitude":"42.84","longitude":"-75.61","state":"NY"},{"latitude":"39.92","longitude":"-121.05","state":"CA"},{"latitude":"40.25","longitude":"-75.14","state":"PA"},{"latitude":"40.33","longitude":"-79.83","state":"PA"},{"latitude":"37.04","longitude":"-76.29","state":"VA"},{"latitude":"37.28","longitude":"-121.2","state":"CA"},{"latitude":"37.27","longitude":"-76.7","state":"VA"},{"latitude":"38.94","longitude":"-119.97","state":"CA"},{"latitude":"37.33","longitude":"-91.83","state":"MO"},{"latitude":"41.6","longitude":"-93.71","state":"IA"},{"latitude":"47.63","longitude":"-117.09","state":"WA"},{"latitude":"34.07","longitude":"-118.01","state":"CA"},{"latitude":"40.43","longitude":"-77.92","state":"PA"},{"latitude":"38.67","longitude":"-91.87","state":"MO"},{"latitude":"41.33","longitude":"-73.88","state":"NY"},{"latitude":"38.251879","longitude":"-94.331993","state":"MO"},{"latitude":"37.22","longitude":"-121.78","state":"CA"},{"latitude":"44.56","longitude":"-103.74","state":"SD"},{"latitude":"41.37","longitude":"-79.25","state":"PA"},{"latitude":"42.17","longitude":"-71.68","state":"MA"},{"latitude":"42.84","longitude":"-76.69","state":"NY"},{"latitude":"33.28","longitude":"-117.19","state":"CA"},{"latitude":"37.96","longitude":"-76.76","state":"VA"},{"latitude":"42.16","longitude":"-75.86","state":"NY"},{"latitude":"41.19","longitude":"-76.3","state":"PA"},{"latitude":"43.8","longitude":"-99.32","state":"SD"},{"latitude":"39.98","longitude":"-76.02","state":"PA"},{"latitude":"34.16","longitude":"-118.21","state":"CA"},{"latitude":"36.9","longitude":"-100.53","state":"OK"},{"latitude":"39.64","longitude":"-119.69","state":"NV"},{"latitude":"35.46","longitude":"-97.51","state":"OK"},{"latitude":"39.72","longitude":"-78.84","state":"PA"},{"latitude":"35.52","longitude":"-95.95","state":"OK"},{"latitude":"41.24","longitude":"-75.87","state":"PA"},{"latitude":"34.25","longitude":"-118.41","state":"CA"},{"latitude":"42.23","longitude":"-93.6","state":"IA"},{"latitude":"34.06","longitude":"-118.08","state":"CA"},{"latitude":"36.903089","longitude":"-100.22748","state":"OK"},{"latitude":"39.95","longitude":"-80.22","state":"PA"},{"latitude":"37.76","longitude":"-117.65","state":"NV"},{"latitude":"36.66","longitude":"-80.7","state":"VA"},{"latitude":"36.62","longitude":"-91.96","state":"MO"},{"latitude":"37.15","longitude":"-82.23","state":"VA"},{"latitude":"35.27","longitude":"-96.03","state":"OK"},{"latitude":"43.76","longitude":"-103.6","state":"SD"},{"latitude":"37.97","longitude":"-90.04","state":"MO"},{"latitude":"40.74","longitude":"-73.08","state":"NY"},{"latitude":"42.27","longitude":"-72.4","state":"MA"},{"latitude":"43.49","longitude":"-92.36","state":"IA"},{"latitude":"36.64","longitude":"-121.62","state":"CA"},{"latitude":"42.5","longitude":"-96.39","state":"IA"},{"latitude":"45.53","longitude":"-100.27","state":"SD"},{"latitude":"44.57","longitude":"-96.64","state":"SD"},{"latitude":"42.91","longitude":"-76.79","state":"NY"},{"latitude":"37.75","longitude":"-78.16","state":"VA"},{"latitude":"43.64","longitude":"-76.06","state":"NY"},{"latitude":"34.16","longitude":"-118.08","state":"CA"},{"latitude":"37.25","longitude":"-121.88","state":"CA"},{"latitude":"38.15","longitude":"-92.44","state":"MO"},{"latitude":"39.09","longitude":"-94.58","state":"MO"},{"latitude":"38.15","longitude":"-91.24","state":"MO"},{"latitude":"39.79","longitude":"-93.55","state":"MO"},{"latitude":"44.35","longitude":"-122.85","state":"OR"},{"latitude":"39.77","longitude":"-75.05","state":"NJ"},{"latitude":"41.52","longitude":"-75.54","state":"PA"},{"latitude":"38.16","longitude":"-121.59","state":"CA"},{"latitude":"36.08","longitude":"-121.6","state":"CA"},{"latitude":"41.71","longitude":"-76.77","state":"PA"},{"latitude":"40.87","longitude":"-73.4","state":"NY"},{"latitude":"35.46","longitude":"-97.51","state":"OK"},{"latitude":"42.39","longitude":"-71.17","state":"MA"},{"latitude":"40.64","longitude":"-73.94","state":"NY"},{"latitude":"42.57","longitude":"-71.29","state":"MA"},{"latitude":"39.09","longitude":"-94.58","state":"MO"},{"latitude":"40.71","longitude":"-73.99","state":"NY"},{"latitude":"42.58","longitude":"-71.43","state":"MA"},{"latitude":"40.31","longitude":"-75.12","state":"PA"},{"latitude":"32.76","longitude":"-117.15","state":"CA"},{"latitude":"40.02","longitude":"-79.94","state":"PA"},{"latitude":"43.58","longitude":"-119.57","state":"OR"},{"latitude":"42.425733","longitude":"-73.899871","state":"NY"},{"latitude":"38.16","longitude":"-94.5","state":"MO"},{"latitude":"40.75","longitude":"-79.53","state":"PA"},{"latitude":"40.71","longitude":"-73.99","state":"NY"},{"latitude":"34.41","longitude":"-117.27","state":"CA"},{"latitude":"42.07","longitude":"-97.96","state":"NE"},{"latitude":"40.82","longitude":"-73.63","state":"NY"},{"latitude":"38.4","longitude":"-122.86","state":"CA"},{"latitude":"43.08","longitude":"-76.87","state":"NY"},{"latitude":"40.26","longitude":"-74.98","state":"PA"},{"latitude":"46.39","longitude":"-124.03","state":"WA"},{"latitude":"37.524246","longitude":"-77.493157","state":"VA"},{"latitude":"40.76","longitude":"-80.05","state":"PA"},{"latitude":"32.9","longitude":"-117.21","state":"CA"},{"latitude":"43.46","longitude":"-76.23","state":"NY"},{"latitude":"41.59","longitude":"-93.23","state":"IA"},{"latitude":"34.16","longitude":"-118.45","state":"CA"},{"latitude":"40.31","longitude":"-79.65","state":"PA"},{"latitude":"38.04","longitude":"-77.06","state":"VA"},{"latitude":"35.33","longitude":"-96.13","state":"OK"},{"latitude":"40.27","longitude":"-76.88","state":"PA"},{"latitude":"39.07","longitude":"-119.79","state":"NV"},{"latitude":"36.73","longitude":"-95.94","state":"OK"},{"latitude":"42.56","longitude":"-92.62","state":"IA"},{"latitude":"38.63","longitude":"-77.67","state":"VA"},{"latitude":"35.29","longitude":"-95.58","state":"OK"},{"latitude":"45.51","longitude":"-122.64","state":"OR"},{"latitude":"40.06","longitude":"-75.4","state":"PA"},{"latitude":"41.57","longitude":"-93.61","state":"IA"},{"latitude":"41.46","longitude":"-91.83","state":"IA"},{"latitude":"43.09","longitude":"-79.01","state":"NY"},{"latitude":"40.27","longitude":"-75.26","state":"PA"},{"latitude":"39.98","longitude":"-79.8","state":"PA"},{"latitude":"42.47","longitude":"-91.59","state":"IA"},{"latitude":"37.08","longitude":"-79.9","state":"VA"},{"latitude":"37.54","longitude":"-77.92","state":"VA"},{"latitude":"43.41","longitude":"-123.11","state":"OR"},{"latitude":"41.7","longitude":"-97.69","state":"NE"},{"latitude":"32.87","longitude":"-114.72","state":"CA"},{"latitude":"42.973468","longitude":"-74.406393","state":"NY"},{"latitude":"42.02","longitude":"-93.62","state":"IA"},{"latitude":"38.72","longitude":"-90.47","state":"MO"},{"latitude":"40.76","longitude":"-73.77","state":"NY"},{"latitude":"35.49","longitude":"-95.3","state":"OK"},{"latitude":"39.95","longitude":"-92.88","state":"MO"},{"latitude":"35.74","longitude":"-98.74","state":"OK"},{"latitude":"39.07","longitude":"-121.84","state":"CA"},{"latitude":"43.16","longitude":"-77.61","state":"NY"},{"latitude":"38.63","longitude":"-90.24","state":"MO"},{"latitude":"37.49","longitude":"-89.72","state":"MO"},{"latitude":"46.45","longitude":"-122.76","state":"WA"},{"latitude":"39.95","longitude":"-123.74","state":"CA"},{"latitude":"36.1","longitude":"-115.02","state":"NV"},{"latitude":"40.94","longitude":"-73.86","state":"NY"},{"latitude":"39.13","longitude":"-77.66","state":"VA"},{"latitude":"42.86","longitude":"-76.98","state":"NY"},{"latitude":"37.76","longitude":"-122.39","state":"CA"},{"latitude":"40.71","longitude":"-74.0","state":"NY"},{"latitude":"37.68","longitude":"-90.75","state":"MO"},{"latitude":"38.55","longitude":"-121.49","state":"CA"},{"latitude":"40.04","longitude":"-76.21","state":"PA"},{"latitude":"44.05","longitude":"-122.05","state":"OR"},{"latitude":"35.08","longitude":"-118.79","state":"CA"},{"latitude":"37.99","longitude":"-92.83","state":"MO"},{"latitude":"47.65","longitude":"-117.37","state":"WA"},{"latitude":"42.06","longitude":"-90.17","state":"IA"},{"latitude":"40.76","longitude":"-94.74","state":"IA"},{"latitude":"43.17","longitude":"-75.29","state":"NY"},{"latitude":"44.24","longitude":"-117.43","state":"OR"},{"latitude":"42.42","longitude":"-78.16","state":"NY"},{"latitude":"34.23","longitude":"-117.23","state":"CA"},{"latitude":"42.44","longitude":"-73.64","state":"NY"},{"latitude":"38.08","longitude":"-79.38","state":"VA"},{"latitude":"42.06","longitude":"-75.42","state":"NY"},{"latitude":"42.6","longitude":"-70.88","state":"MA"},{"latitude":"42.88","longitude":"-78.85","state":"NY"},{"latitude":"39.69","longitude":"-74.25","state":"NJ"},{"latitude":"40.06","longitude":"-74.68","state":"NJ"},{"latitude":"38.13","longitude":"-92.65","state":"MO"},{"latitude":"36.75","longitude":"-119.67","state":"CA"},{"latitude":"37.19","longitude":"-93.28","state":"MO"},{"latitude":"38.35","longitude":"-90.98","state":"MO"},{"latitude":"40.83","longitude":"-74.48","state":"NJ"},{"latitude":"40.24","longitude":"-97.38","state":"NE"},{"latitude":"40.0","longitude":"-97.76","state":"NE"},{"latitude":"42.47","longitude":"-95.78","state":"IA"},{"latitude":"40.49","longitude":"-75.68","state":"PA"},{"latitude":"40.13","longitude":"-97.72","state":"NE"},{"latitude":"39.74","longitude":"-79.81","state":"PA"},{"latitude":"39.9","longitude":"-77.34","state":"PA"},{"latitude":"37.55","longitude":"-77.46","state":"VA"},{"latitude":"34.52","longitude":"-97.96","state":"OK"},{"latitude":"40.71","longitude":"-73.26","state":"NY"},{"latitude":"37.19","longitude":"-93.28","state":"MO"},{"latitude":"37.17","longitude":"-92.85","state":"MO"},{"latitude":"41.08","longitude":"-96.13","state":"NE"},{"latitude":"41.64","longitude":"-99.37","state":"NE"},{"latitude":"48.62","longitude":"-123.01","state":"WA"},{"latitude":"42.61","longitude":"-71.62","state":"MA"},{"latitude":"40.46","longitude":"-96.37","state":"NE"},{"latitude":"34.62","longitude":"-96.63","state":"OK"},{"latitude":"41.76","longitude":"-75.78","state":"PA"},{"latitude":"41.0","longitude":"-74.2","state":"NJ"},{"latitude":"38.68","longitude":"-121.34","state":"CA"},{"latitude":"34.0","longitude":"-118.1","state":"CA"},{"latitude":"34.37","longitude":"-96.42","state":"OK"},{"latitude":"37.1","longitude":"-93.81","state":"MO"},{"latitude":"37.19","longitude":"-121.83","state":"CA"},{"latitude":"38.87","longitude":"-119.14","state":"NV"},{"latitude":"40.04","longitude":"-78.64","state":"PA"},{"latitude":"41.66","longitude":"-70.93","state":"MA"},{"latitude":"38.87","longitude":"-77.1","state":"VA"},{"latitude":"40.71","longitude":"-73.99","state":"NY"},{"latitude":"41.86","longitude":"-75.51","state":"PA"},{"latitude":"42.34","longitude":"-75.05","state":"NY"},{"latitude":"33.1","longitude":"-117.29","state":"CA"},{"latitude":"42.06","longitude":"-72.21","state":"MA"},{"latitude":"42.35","longitude":"-71.06","state":"MA"},{"latitude":"39.37","longitude":"-75.21","state":"NJ"},{"latitude":"33.18","longitude":"-117.24","state":"CA"},{"latitude":"37.381144","longitude":"-122.334825","state":"CA"},{"latitude":"35.2","longitude":"-95.88","state":"OK"},{"latitude":"43.54","longitude":"-96.72","state":"SD"}]
